Workbook

Sheet Cash Flow
A1: EXAMPLE COMPANY PRIVATE LIMITED
A2: Budget: Cash Flow (fictional)
A3: 46319 | B3: Fund Available - | D3: 1350000
A4: Due Date | B4: Payments \ (Receipts) | C4: Head | D4: IN Rupees | E4: Balance | F4: Done (1/0) | G4: Remarks if any
A5: =A3 | B5: Opening bank balance (fund available) | E5: =D3 | F5: 1
A6: 46310 | B6: Vendor X balance payment | C6: Vendor | D6: 50000 | E6: =E5 | F6: 1 | G6: Done: already in opening balance
A7: 46317 | B7: Client A invoice 1 | C7: Receipt | D7: -300000 | E7: =E6 | F7: 1 | G7: Received: already in opening balance
A8: 46321 | B8: Project Alpha fittings | C8: Project Alpha | D8: 100000 | E8: =E7-N(D8)
A9: 46321 | B9: Client A advance | C9: Receipt | D9: -200000 | E9: =E8-N(D9)
A10: 46331 | B10: Salary Sep | C10: Monthly | D10: 400000 | E10: =E9-N(D10)
A11: 46361 | B11: Salary Oct | C11: Monthly | D11: =D10 | E11: =E10-N(D11)
A12: 46392 | B12: Salary Nov | C12: Monthly | D12: =D10 | E12: =E11-N(D12)
A13: 46477 | B13: Software licence | C13: Software | D13: 90000 | E13: =E12-N(D13)
A14: 46477 | B14: Closing balance at end of cash flow period | E14: =E13
B15: Lowest balance in the period | E15: =MIN(E5:E13) | G15: ="on "&TEXT(INDEX(A5:A13,MATCH(MIN(E5:E13),E5:E13,0)),"dd-mmm-yy")

Sheet Month Summary
A1: EXAMPLE COMPANY: month-wise summary
A4: Month | B4: Opening balance | C4: Receipts (in) | D4: Payments (out) | E4: Closing balance | F4: Lowest balance in month | G4: Check
A5: 46296 | B5: ='Cash Flow'!D3 | C5: =-SUMIFS('Cash Flow'!$D$5:$D$13,'Cash Flow'!$A$5:$A$13,">="&H5,'Cash Flow'!$A$5:$A$13,"<="&I5,'Cash Flow'!$D$5:$D$13,"<0") | D5: =SUMIFS('Cash Flow'!$D$5:$D$13,'Cash Flow'!$A$5:$A$13,">="&H5,'Cash Flow'!$A$5:$A$13,"<="&I5,'Cash Flow'!$D$5:$D$13,">0") | E5: =B5+C5-D5 | F5: =MIN(B5,_xlfn.MINIFS('Cash Flow'!$E$5:$E$13,'Cash Flow'!$A$5:$A$13,">="&H5,'Cash Flow'!$A$5:$A$13,"<="&I5)) | G5: =IF(F5<0,"Shortfall","") | H5: 46319 | I5: 46326
A6: 46327 | B6: =E5 | C6: =-SUMIFS('Cash Flow'!$D$5:$D$13,'Cash Flow'!$A$5:$A$13,">="&H6,'Cash Flow'!$A$5:$A$13,"<="&I6,'Cash Flow'!$D$5:$D$13,"<0") | D6: =SUMIFS('Cash Flow'!$D$5:$D$13,'Cash Flow'!$A$5:$A$13,">="&H6,'Cash Flow'!$A$5:$A$13,"<="&I6,'Cash Flow'!$D$5:$D$13,">0") | E6: =B6+C6-D6 | F6: =MIN(B6,_xlfn.MINIFS('Cash Flow'!$E$5:$E$13,'Cash Flow'!$A$5:$A$13,">="&H6,'Cash Flow'!$A$5:$A$13,"<="&I6)) | G6: =IF(F6<0,"Shortfall","") | H6: 46327 | I6: 46356
A7: 46357 | B7: =E6 | C7: =-SUMIFS('Cash Flow'!$D$5:$D$13,'Cash Flow'!$A$5:$A$13,">="&H7,'Cash Flow'!$A$5:$A$13,"<="&I7,'Cash Flow'!$D$5:$D$13,"<0") | D7: =SUMIFS('Cash Flow'!$D$5:$D$13,'Cash Flow'!$A$5:$A$13,">="&H7,'Cash Flow'!$A$5:$A$13,"<="&I7,'Cash Flow'!$D$5:$D$13,">0") | E7: =B7+C7-D7 | F7: =MIN(B7,_xlfn.MINIFS('Cash Flow'!$E$5:$E$13,'Cash Flow'!$A$5:$A$13,">="&H7,'Cash Flow'!$A$5:$A$13,"<="&I7)) | G7: =IF(F7<0,"Shortfall","") | H7: 46357 | I7: 46387
A8: 46388 | B8: =E7 | C8: =-SUMIFS('Cash Flow'!$D$5:$D$13,'Cash Flow'!$A$5:$A$13,">="&H8,'Cash Flow'!$A$5:$A$13,"<="&I8,'Cash Flow'!$D$5:$D$13,"<0") | D8: =SUMIFS('Cash Flow'!$D$5:$D$13,'Cash Flow'!$A$5:$A$13,">="&H8,'Cash Flow'!$A$5:$A$13,"<="&I8,'Cash Flow'!$D$5:$D$13,">0") | E8: =B8+C8-D8 | F8: =MIN(B8,_xlfn.MINIFS('Cash Flow'!$E$5:$E$13,'Cash Flow'!$A$5:$A$13,">="&H8,'Cash Flow'!$A$5:$A$13,"<="&I8)) | G8: =IF(F8<0,"Shortfall","") | H8: 46388 | I8: 46418
A9: 46419 | B9: =E8 | C9: =-SUMIFS('Cash Flow'!$D$5:$D$13,'Cash Flow'!$A$5:$A$13,">="&H9,'Cash Flow'!$A$5:$A$13,"<="&I9,'Cash Flow'!$D$5:$D$13,"<0") | D9: =SUMIFS('Cash Flow'!$D$5:$D$13,'Cash Flow'!$A$5:$A$13,">="&H9,'Cash Flow'!$A$5:$A$13,"<="&I9,'Cash Flow'!$D$5:$D$13,">0") | E9: =B9+C9-D9 | F9: =MIN(B9,_xlfn.MINIFS('Cash Flow'!$E$5:$E$13,'Cash Flow'!$A$5:$A$13,">="&H9,'Cash Flow'!$A$5:$A$13,"<="&I9)) | G9: =IF(F9<0,"Shortfall","") | H9: 46419 | I9: 46446
A10: 46447 | B10: =E9 | C10: =-SUMIFS('Cash Flow'!$D$5:$D$13,'Cash Flow'!$A$5:$A$13,">="&H10,'Cash Flow'!$A$5:$A$13,"<="&I10,'Cash Flow'!$D$5:$D$13,"<0") | D10: =SUMIFS('Cash Flow'!$D$5:$D$13,'Cash Flow'!$A$5:$A$13,">="&H10,'Cash Flow'!$A$5:$A$13,"<="&I10,'Cash Flow'!$D$5:$D$13,">0") | E10: =B10+C10-D10 | F10: =MIN(B10,_xlfn.MINIFS('Cash Flow'!$E$5:$E$13,'Cash Flow'!$A$5:$A$13,">="&H10,'Cash Flow'!$A$5:$A$13,"<="&I10)) | G10: =IF(F10<0,"Shortfall","") | H10: 46447 | I10: 46477
A11: TOTAL | C11: =SUM(C5:C10) | D11: =SUM(D5:D10) | E11: =E10 | G11: =IF(ROUND(E11-'Cash Flow'!E14,2)=0,"OK","Mismatch")
